romhacking_rss/__init__.py
romhacking_rss/main.py
tests/__init__.py
tests/test_main.py
romhacking_rss-1.0.0.dist-info/LICENSE
romhacking_rss-1.0.0.dist-info/METADATA
romhacking_rss-1.0.0.dist-info/WHEEL
romhacking_rss-1.0.0.dist-info/entry_points.txt
romhacking_rss-1.0.0.dist-info/top_level.txt
romhacking_rss-1.0.0.dist-info/zip-safe
romhacking_rss-1.0.0.dist-info/RECORD
