Metadata-Version: 2.1
Name: romhacking-rss
Version: 1.0.0
Summary: Ingest a romhacking search topic and render as RSS
Home-page: https://github.com/narfman0/romhacking-rss
Author: Jon Robison
Author-email: narfman0@gmail.com
License: LICENSE
Keywords: romhacking rss atom flask
Platform: UNKNOWN
Classifier: Development Status :: 4 - Beta
Classifier: License :: OSI Approved :: GNU General Public License v3 (GPLv3)
Classifier: Operating System :: OS Independent
Classifier: Programming Language :: Python
Classifier: Topic :: Software Development :: Libraries :: Python Modules
Requires-Dist: beautifulsoup4
Requires-Dist: Werkzeug (==0.16.0)
Requires-Dist: flask
Requires-Dist: requests
